rpc_zigzag-1.0.0.dist-info/METADATA
rpc_zigzag-1.0.0.dist-info/RECORD
rpc_zigzag-1.0.0.dist-info/WHEEL
rpc_zigzag-1.0.0.dist-info/entry_points.txt
rpc_zigzag-1.0.0.dist-info/top_level.txt
zigzag/__init__.py
zigzag/cli.py
zigzag/link_generation_facade.py
zigzag/module_hierarchy_facade.py
zigzag/requirements_link_facade.py
zigzag/utility_facade.py
zigzag/xml_parsing_facade.py
zigzag/zigzag.py
zigzag/zigzag_config.py
zigzag/zigzag_error.py
zigzag/zigzag_test_log.py
zigzag/data/junit.xsd
zigzag/data/configs/mk8s-config-example.json
zigzag/data/configs/molecule-config-example.json
zigzag/data/configs/zigzag-config-example.json
zigzag/data/schema/zigzag-config.schema.json
