Metadata-Version: 2.1
Name: rpc-zigzag
Version: 1.0.0
Summary: Parse JUnitXML and upload test results to qTest Manager.
Home-page: https://github.com/rcbops/zigzag
Author: rcbops
Author-email: rcb-deploy@lists.rackspace.com
Maintainer: rcbops
Maintainer-email: rcb-deploy@lists.rackspace.com
License: Apache Software License 2.0
Keywords: zigzag
Platform: UNKNOWN
Classifier: Development Status :: 4 - Beta
Classifier: Intended Audience :: Developers
Classifier: License :: OSI Approved :: Apache Software License
Classifier: Natural Language :: English
Classifier: Programming Language :: Python :: 2
Classifier: Programming Language :: Python :: 2.7
Classifier: Programming Language :: Python :: 3
Classifier: Programming Language :: Python :: 3.4
Classifier: Programming Language :: Python :: 3.5
Classifier: Programming Language :: Python :: 3.6
Classifier: Operating System :: OS Independent
Requires-Dist: Click (>=6.0)
Requires-Dist: lxml
Requires-Dist: rpc-qtest-swagger-client (<10.0.0)
Requires-Dist: requests
Requires-Dist: jsonschema
Requires-Dist: future
Requires-Dist: jinja2
